[
    {
        "id": 1,
        "category": "門診異動",
        "tagClass": "tag-blue",
        "date": "2026/06/01",
        "title": "6、7月份各院區醫師門診異動與代診公告",
        "excerpt": "為提供更完善的醫療服務，本院及相關院區部分醫師於6月及7月份將進行門診時間調整，包含多位醫師之停診與代診資訊，敬請就診前多加留意。",
        "content": "<h3>心臟內科 李坤泰醫師</h3><ul><li>6/9(二) 廣東路 李氏聯合診所 上午 停診</li></ul><h3>新陳代謝科 溫緯倫醫師</h3><ul><li>6/1(一) 潮州 真善美診所 上午、下午 當診醫師代診</li><li>6/9(二) 潮州 真善美診所 下午 崔煥文醫師代診</li><li>6/15(一) 潮州 真善美診所 上午 李坤泰醫師代診</li><li>6/15(一) 潮州 真善美診所 下午 崔煥文醫師代診</li><li>6/16(二) 潮州 真善美診所 下午 崔煥文醫師代診</li><li>6/16(二) 潮州 真善美診所 晚上 休診</li><li>6/17(三) 潮州 真善美診所 下午、晚上 莊立倫醫師代診</li><li>6/18(四) 建豐路 瑞基診所 下午 詹益世醫師代診</li></ul><h3>神經內科 崔煥文醫師</h3><ul><li>6/12(五) 廣東路 李氏聯合診所 上午 停診</li></ul><h3>新陳代謝科 莊立倫醫師</h3><ul><li>6/9(二) 潮州 美新診所 下午 溫緯倫醫師代診</li><li>6/12(五) 鳳山 文山診所 上午 當診醫師代診</li><li>7/1(三) 鳳山 文山診所 上午、下午 停診</li><li>7/3(五) 鳳山 文山診所 上午 停診</li></ul><h3>新陳代謝科 李洮俊醫師</h3><ul><li>6/4(四) 民族路 李洮俊診所 上午 當診醫師代診</li><li>6/5(五) 廣東路 李氏聯合診所 上午 張毓泓醫師代診</li><li>6/6(六) 潮州 真善美診所 上午 當診醫師代診</li><li>6/8(一) 東港 陳秋安診所 上午 陳秋安醫師代診</li><li>6/9(二) 民族路 李洮俊診所 上午 李坤泰醫師代診</li><li>6/10(三) 廣東路 李氏聯合診所 張毓泓醫師代診</li></ul><h3>新陳代謝科 胡德瑋醫師</h3><ul><li>6/1(一) 民族路 李洮俊診所 上午、下午 溫緯倫醫師代診</li><li>6/1(一) 民族路 李洮俊診所 晚上 休診</li><li>6/12(五) 潮州 真善美診所 上午 崔煥文醫師代診</li></ul><h3>新陳代謝科 張毓泓醫師</h3><ul><li>6/19(五) 廣東路 李氏聯合診所 下午、晚上 當診醫師代診</li></ul><h3>腎臟科 藍文君醫師</h3><ul><li>6/20(六) 廣東路 李氏聯合診所 上午 休診</li></ul><h3>腎臟科 王繼樟醫師</h3><ul><li>6/12(五) 潮州 美新診所 上午 莊立倫醫師代診</li><li>6/30(二) 潮州 美新診所 上午 莊立倫醫師代診</li><li>6/30(二) 鳳山 文山診所 下午 蔡怡萱醫師代診</li><li>7/1(三)~7/3(五) 潮州 美新診所 上午、下午 莊立倫醫師代診</li><li>7/1(三) 鳳山 文山診所 晚上 吳淑蓉醫師代診</li></ul><h3>腎臟科 劉冠逸醫師</h3><ul><li>6/9(二) 民族路 李洮俊診所 上午 李坤泰醫師代診</li><li>6/9(二) 建豐路 瑞基診所 下午 藍文君醫師代診</li><li>6/10(三) 建豐路 瑞基診所 下午 詹益世醫師代診</li><li>6/11(四) 廣東路 李氏聯合診所 上午、下午 休診</li><li>6/12(五) 廣東路 李氏聯合診所 上午 藍文君醫師代診</li><li>6/12(五) 廣東路 李氏聯合診所 下午、晚上 休診</li></ul>"
    },
    {
        "id": 2,
        "category": "疫苗活動",
        "tagClass": "tag-green",
        "date": "2026/05/18",
        "image": "image/695.jpg",
        "title": "公費肺炎鏈球菌疫苗開始接種，符合資格長者請盡速預約",
        "excerpt": "為守護長者健康、降低肺炎及相關感染風險，本診所及相關院區即日起提供公費肺炎鏈球菌疫苗接種服務，符合資格之長者歡迎洽詢預約。",
        "content": "<p>為守護長者健康、降低肺炎及相關感染風險，本診所將提供公費肺炎鏈球菌疫苗接種服務。</p><ul><li>✅ 李氏聯合診所（洮俊診所/張道明診所/藍文君診所）／李洮俊診所 自 115年6月1日起，開始提供公費肺炎鏈球菌疫苗注射服務。</li><li>✅ 真善美診所仍持續提供公費肺炎鏈球菌疫苗注射服務。</li></ul><p>凡 65歲以上且符合公費接種資格，並有接種需求之民眾，歡迎洽詢各診所，相關資訊可參考：<a href=\"https://www.facebook.com/pth272/posts/pfbid02Ujg5qx5VBue3Fh9FJL5aDSB59M41wwTM1GMvj5MSqNpABRGATW1D4LWdLdP4Az2Nl?rdid=nFamWkrUV6LJoyY2#\" target=\"_blank\">李氏聯合診所 Facebook 粉絲專頁公告</a></p><h3>聯絡與洽詢專線</h3><ul><li>☎️廣東路：(08)736-3766</li><li>☎️民族路：(08)766-8901</li><li>☎️真善美：(08)789-5123</li></ul><p>守護自己與家人的健康，從預防開始💪<br>李氏聯合診所 關心您</p>"
    },
    {
        "id": 3,
        "category": "醫療新知",
        "tagClass": "tag-blue",
        "date": "2026/05/10",
        "image": "image/656.png",
        "title": "長者量六力｜用 LINE 隨時掌握健康狀況",
        "excerpt": "國民健康署推出「長者量六力」LINE 官方帳號，提供 65 歲以上長者與家屬隨時進行自我健康檢測",
        "content": "<p>手機在手，健康不用愁！國民健康署推出「長者量六力」LINE 官方帳號，提供 65 歲以上長者與家屬隨時進行自我健康檢測。</p><h3>「量六力」包含六大功能：</h3><ul><li>✅ 認知</li><li>✅ 行動</li><li>✅ 營養</li><li>✅ 視力</li><li>✅ 聽力</li><li>✅ 情緒</li></ul><p>透過定期檢測，可幫助及早發現身心功能變化，預防及延緩失能。加入後，還能接收健康衛教資訊、互動小遊戲、健康食譜，並查詢附近社區資源與醫療院所。</p><p>家中長輩的健康，從定期「量六力」開始！歡迎長者及家屬立即加入 LINE 好友：</p><ul><li>🔍 搜尋 ID：@hpaicope</li><li>📱 或掃描圖中 QR code 加入好友</li></ul><p>📌 加入好友操作方法請參考：<a href=\"https://youtu.be/wodNgrNi0po?si=2w1jqktIyXF9-LQ7\" target=\"_blank\">YouTube 教學影片</a></p><p>一起為長輩健康把關💚</p>"
    },
    {
        "id": 4,
        "category": "醫療新知",
        "tagClass": "tag-green",
        "date": "2026/04/22",
        "image": "image/9644.jpg",
        "title": "害怕跌倒後更不敢動？認識「跌倒恐懼」與克服指南",
        "excerpt": "長者跌倒後，常因害怕再次跌倒而減少活動，導致肌力下降、步態不穩，反而增加再跌倒風險。由陳秋安診所許英凌護理師教您如何幫助長者重新找回行動力與自信。",
        "content": "<p><strong>文 / 陳秋安診所 許英凌護理師</strong></p><p>長者跌倒後，常因害怕再次跌倒而減少活動，導致肌力下降、步態不穩，反而增加再跌倒風險。這種惡性循環，被稱為「跌倒恐懼」或「跌倒後症候群」。</p><h3>📌 常見情形包括：</h3><ul><li>1️⃣ 不敢外出</li><li>2️⃣ 走路緩慢僵硬</li><li>3️⃣ 需要扶牆行走</li><li>4️⃣ 容易焦慮</li><li>5️⃣ 失眠</li><li>6️⃣ 情緒低落或憂鬱</li></ul><h3>📌 如何幫助長者重新找回行動力？</h3><p>可以透過以下方式，逐步恢復行動能力與自信：</p><ul><li>✅ 下肢肌力訓練</li><li>✅ 平衡訓練</li><li>✅ 步態訓練</li></ul><p>並採取漸進式活動方式：</p><ul><li>▪️ 室內短距離步行 🚶‍♀️</li><li>▪️ 有人陪伴散步 ❤️</li><li>▪️ 使用助行器增加安全感</li></ul><h3>📌 居家安全也很重要 🏡</h3><p>建議：</p><ul><li>▪️ 移除地面雜物</li><li>▪️ 增加照明 💡</li><li>▪️ 浴室加裝止滑設備</li><li>▪️ 穿著防滑鞋 👟</li></ul><p>這些都能有效降低跌倒風險 ⚠️</p><h3>📌 若害怕跌倒已影響生活</h3><p>可透過「認知行為治療」協助調整負面想法，家屬也應多陪伴與鼓勵，避免過度限制行動，重新建立安全活動的信心。</p><h3>📌 此外，也可以鼓勵長者參與：</h3><ul><li>▪️ 社區運動課程</li><li>▪️ 復健訓練</li><li>▪️ 防跌衛教活動</li></ul><p>增加人際互動與身體活動量，規律運動不僅能提升肌力與平衡感，也能降低焦慮感與對跌倒的過度擔憂。過程中請耐心傾聽長者感受，一步一步建立安全感與自信！</p>"
    },
    {
        "id": 101,
        "category": "糖尿病專區",
        "tagClass": "tag-green",
        "date": "2026/04/22",
        "image": "image/634.png",
        "title": "「糖尿病前期」逆轉勝",
        "excerpt": "罹患糖尿病初期是沒有症狀的，多數人往往等到出現多吃、多喝、多尿或體重減輕的症狀時，才驚覺自己有糖尿病。趕快來看看您是否為候選人，以及如何逆轉勝！",
        "content": "<p><strong>🔸文 / 李氏聯合診所 李佩儒衛教師</strong></p><h3>🧣您是糖尿病候選人嗎❓</h3><p>罹患糖尿病初期是沒有症狀的，多數人往往等到出現多吃、多喝、多尿或體重減輕的症狀時，才驚覺自己有糖尿病，錯失早期改善的機會。檢視自己若有下列情形之一，即處於「糖尿病前期」的階段，即是糖尿病的候選人了。</p><p style=\"text-align: center; font-weight: bold; color: #d9534f; font-size: 1.1rem; margin: 20px 0;\">👉 請看封面大圖說明 👈</p><h3>🧣糖尿病前期有什麼風險❓</h3><p>據調查，糖尿病前期民眾有66%腰圍超標、65%有過重或肥胖情形。這些人約有5-10%會發展為糖尿病，同時也會增加罹患心血管疾病或慢性腎臟病風險。</p><h3>🧣「糖尿病前期」逆轉勝的祕訣</h3><p>糖尿病前期是可以逆轉的，以下行動可以有效阻斷發展成為糖尿病：</p><ul><li>1️⃣ <strong>改善生活型態：</strong>鼓勵減重 5-10%，每週 150 分鐘以上之中等強度的運動 ⛹️‍♀️。</li><li>2️⃣ <strong>定期監測血糖值：</strong>建議每年檢測空腹血糖或糖化血色素或口服葡萄糖耐受試驗。</li></ul><hr style=\"border: 0; border-top: 1px dashed #ccc; margin: 25px 0;\"><p style=\"font-size: 0.85rem; color: #888; line-height: 1.6;\"><strong>🔹參考資料：</strong><br>著作者：社團法人中華民國糖尿病學會（2022）。<br>書名：2022 第 2 型糖尿病臨床照護指引。<br>出版地：台北市。出版者：社團法人中華民國糖尿病學會(2022)</p>"
    },
    {
        "id": 102,
        "category": "腎臟專區",
        "tagClass": "tag-green",
        "date": "2026/04/22",
        "image": "image/6378.png",
        "title": "護腎5部曲：請跟我們這樣做",
        "excerpt": "大家應該要好好愛護自己的腎臟，提供護腎五部曲：戒菸減重、謹「腎」飲食、控制三高、正確就醫及自我監測，一起來保腎護心！",
        "content": "<p><strong>🔸文/李氏聯合診所 許英凌衛教師</strong></p><p>大家應該要好好愛護自己的腎臟，如何愛護呢❓<br>提供護腎五部曲，請跟我們這樣做🙋‍♀️</p><h3>🎼一部曲：戒菸🚫減重、健康生活</h3><h3>🎼二部曲：謹「腎」飲食、少油少鹽少糖🥗</h3><p>雖然食物會比較有味道，但增加身體腎臟的負擔</p><h3>🎼三部曲：控制三高、保腎護心</h3><h3>🎼四部曲：正確就醫、不亂吃藥💊</h3><p>配合醫護人員教導，停藥不擅自增加或減量喔</p><h3>🎼五部曲：自我監測、定期追蹤🔍</h3><p>請留意小便🚽，解完後勿馬上沖水，等待約15分鐘後，觀察尿液是否有變化，如有小泡泡，當無法自行判讀時勿過度驚慌或忽視它，可至醫療院所做檢驗。</p><hr style=\"border: 0; border-top: 1px dashed #ccc; margin: 25px 0;\"><p>❇️請每年至少做一次尿蛋白及腎功能檢查追蹤，包括尿液及血液檢查。</p><p>❇️若有腎臟照護問題，請諮詢李氏聯合診所腎臟內科醫師或腎臟衛教護理師為您解答</p>"
    },
    {
        "id": 103,
        "category": "代謝症候群專區",
        "tagClass": "tag-green",
        "date": "2026/04/22",
        "image": "image/99.png",
        "title": "代謝症候群不上身，從生活小改變開始！",
        "excerpt": "代謝症候群是多種健康問題的前兆，像是腹部肥胖、血糖異常、血壓高、血脂不正常……若不改善，恐引發糖尿病、心血管疾病！想要遠離它，你可以這樣做。",
        "content": "<p><strong>🔸文/李氏聯合診所 張家蓉衛教師</strong></p><p>代謝症候群是多種健康問題的前兆，像是腹部肥胖、血糖異常、血壓高、血脂不正常……若不改善，恐引發糖尿病、心血管疾病❗</p><h3>📌想要遠離代謝症候群，你可以這樣做：</h3><ul><li><strong>🥗 吃得健康：</strong>多吃蔬果、豆類、全穀；少吃加工食品和含糖飲料，記得細嚼慢嚥不過量。</li><li><strong>🏃 動一動：</strong>每天走走路、爬樓梯，目標每週150分鐘中等強度運動。找到自己喜歡的活動最重要！</li><li><strong>🛌 睡得夠：</strong>每天固定時間上床，睡滿7–9小時，幫助穩定荷爾蒙與食慾。</li><li><strong>💆 壓力減少點：</strong>緊張時深呼吸、散步或寫日記。找人聊聊，比自己悶著有效多了。</li><li><strong>🚭 遠離傷身物質：</strong>戒菸、減少喝酒，也要避免接觸太多化學加工品。</li><li><strong>👨‍👩‍👧‍👦 有人陪伴：</strong>與家人朋友保持聯繫、參加社區活動，生活多一點動力！</li></ul><p>你不需要一次做到全部，從今天起多吃一道青菜、提早半小時睡覺、或多走500步，都是邁向健康的開始✨</p><p>健康不是靠急，而是靠每天的溫柔堅持。</p><hr style=\"border: 0; border-top: 1px dashed #ccc; margin: 25px 0;\"><p style=\"font-size: 0.85rem; color: #888;\"><strong>🔸參考資料：</strong>衛福部國民健康署健康九九</p>"
    },
    {
        "id": 104,
        "category": "護理專區",
        "tagClass": "tag-green",
        "date": "2026/04/22",
        "image": "image/974.png",
        "title": "如何避免長者骨質疏鬆症",
        "excerpt": "老年人及停經婦女為骨質疏鬆症的高危險族群，若骨質不佳，跌倒骨折的風險將大幅增加。由顏素瑛護理師教您如何檢查與預防骨質疏鬆！",
        "content": "<p><strong>🔸文/李氏聯合診所 顏素瑛護理師</strong></p><p>老年人及停經婦女為骨質疏鬆症的高危險族群，當上了年紀後，因走路🚶‍♀️姿勢改變，跌倒的機會增加，如骨質不好，骨折的風險就更大了。</p><h3>🦴什麼是骨質疏鬆症❓</h3><p>當骨骼因骨量減少或骨質密度降低↘️</p><h3>🦴骨質疏鬆症如何檢查❓</h3><ul><li>🔹<strong>超音波：</strong>測量腳踝、手腕或手指的骨質密度。</li><li>🔹<strong>低劑量X光：</strong>檢查腰椎或大腿骨。</li></ul><p>檢查結果以T值呈現，T值≧ -1 表示是正常的骨質，介於-1與-2.5之間則稱為骨質流失或骨質減少，當T值≦ -2.5則表示骨質疏鬆症。</p><h3>🦴如何降低骨質疏鬆的危害❓</h3><p>預防勝於治療，骨質疏鬆症也不例外，除了注重平時的生活飲食🥪，攝取足夠的鈣質🧀與維他命D、適度的陽光曝曬☀️、適度的運動🏃‍♀️，以及不喝酒❌🍷與不吸菸🚭，皆是對骨質密度有利的生活習慣，降低罹患骨質疏鬆症的危險。在居家環境上也應保持走道明亮💡，平坦地面，排除妨礙通行的障礙物，以避免跌倒。</p>"
    },
    {
        "id": 105,
        "category": "藥物專區",
        "tagClass": "tag-green",
        "date": "2026/04/22",
        "image": "image/321.png",
        "title": "腎臟功能已經不好了，吃這麼多藥會不會更傷腎？",
        "excerpt": "許多人擔心吃藥傷腎，但控制好慢性病其實能延緩腎功能下降！由專業藥師為您解答用藥迷思，教您如何正確保腎護心。",
        "content": "<p><strong>🔸文/博美藥局 吳廷育藥師</strong></p><ul><li style=\"margin-bottom: 10px;\">📒除了腎臟病家族史之外，高血壓、高血糖、高血脂、老化、肥胖、長期服藥、長期使用止痛藥、高尿酸、吸菸🚬等生活型態為造成慢性腎臟病的主要原因。</li><li style=\"margin-bottom: 10px;\">📒沒有專業人員諮詢下，自行購買的止痛藥、來路不明的中草藥(如:馬兜鈴酸)，影像檢查的顯影劑和特定抗生素都可能會造成腎臟功能急速下降⬇️。</li><li style=\"margin-bottom: 10px;\">📒<strong>研究證實，控制好慢性病可以延緩腎臟功能下降</strong>，所以降血壓、降血糖、降血脂、降尿酸的藥物務必規律服用，避免現有慢性病控制不佳，更容易導致腎臟衰竭進程加快😱。</li><li style=\"margin-bottom: 10px;\">📒另外，可以減少蛋白尿的藥物(如: pentoxifylline、SGLT2i..等)，可減緩腎臟功能惡化的速度，也是建議要規律來使用。</li><li style=\"margin-bottom: 10px;\">📒<strong>務必規律回診</strong>，🧑‍⚕️醫師定期追蹤腎臟功能指數及尿蛋白，依腎臟功能調整藥物劑量，減少腎臟負擔。並依照疾病的現況開立貧血、水腫、電解質不平衡等藥物，即便這些用藥可能需要長期服用，也不需要過份擔憂而抗拒使用藥物。</li></ul><hr style=\"border: 0; border-top: 1px dashed #ccc; margin: 25px 0;\"><p style=\"font-size: 0.85rem; color: #888;\"><strong>🔹資料來源：</strong>台灣慢性腎臟病臨床診療指引(台灣腎臟醫學會)</p>"
    },
    {
        "id": 106,
        "category": "眼睛保健專區",
        "tagClass": "tag-green",
        "date": "2026/04/22",
        "image": "image/31.png",
        "title": "改善惱人飛蚊症，3招護眼祕訣",
        "excerpt": "眼前經常出現點狀、線狀或黑影在漂游嗎？這可能是「飛蚊症」的徵兆。由專業護理師教您3招日常護眼秘訣，幫助改善惱人的飛蚊症！",
        "content": "<p><strong>🔸文 / 李氏聯合診所 鄒宛容護理師</strong></p><p>🔍「飛蚊症」只是一種病人自覺的徵候，會看到眼前有不明飛行物，可以是點狀、線狀、面狀，甚至是立體狀的黑影在眼前漂游，這是因為眼睛視網膜內部出現雜質時，自然就成為患者所看到的飛行物。</p><h3>👁️改善飛蚊症 3招護眼👁️</h3><ul><li style=\"margin-bottom: 10px;\"><strong>👀第1招：</strong>飛蚊症是玻璃體變化的視象，減少過度用眼📱。</li><li style=\"margin-bottom: 10px;\"><strong>👀第2招：</strong>平時可以開始「養」眼，多攝取抗氧化食物，並從牛奶🥛、蛋🥚、魚、全穀物及豆類、深綠色蔬菜🥬和蔬果補充營養，也可以適度攝取葉黃素、魚油等營養品。</li><li style=\"margin-bottom: 10px;\"><strong>👀第3招：</strong>應該3個月到1年內做1次定期追蹤🔍。</li></ul><hr style=\"border: 0; border-top: 1px dashed #ccc; margin: 25px 0;\"><p style=\"font-size: 0.85rem; color: #888; line-height: 1.6;\"><strong>🔹參考資料：</strong><br>華人健康網 撰文者張世傑 <a href=\"https://health.businessweekly.com.tw/AArticle.aspx?id=ARTL000056824\" target=\"_blank\" rel=\"noopener noreferrer\" style=\"color: #0088cc;\">原文連結</a><br>中國醫藥大學附設醫院 衛教健康分享網 <a href=\"https://www.ca2-health.com/oph\" target=\"_blank\" rel=\"noopener noreferrer\" style=\"color: #0088cc;\">原文連結</a></p>"
    },
    {
        "id": 107,
        "category": "心血管專區",
        "tagClass": "tag-green",
        "date": "2026/04/22",
        "image": "image/21.png",
        "title": "心臟怦怦跳，我有心臟病嗎？",
        "excerpt": "當你突然感到心臟撲通撲通跳，不論是感覺心跳加快、變慢或漏拍，這就是心悸。由專業護理師帶您了解心悸何時該就醫以及常見的診斷方法！",
        "content": "<p><strong>🔸文/李氏聯合診所 林宥利護理師</strong></p><h3>❇️什麼是心悸❓</h3><p>當你突然感到心臟正撲通撲通跳，不論是感覺心跳加快、變慢、漏拍或是強度變強，就是所謂的心悸。</p><h3>❇️什麼時候該就醫❓</h3><p>若有心臟病史、心悸持續時間長、靜止心率高於100次/分鐘，便需要接受相關檢查。<strong>若心悸合併發生胸痛、胸悶、手臂、脖子、上背疼痛、嚴重呼吸困難、頭暈或冒冷汗的狀況，請立即就醫🏥。</strong></p><h3>❇️心悸的診斷方法</h3><p>醫師會先用聽診器聽你的心音，了解你的過往病史，並可能安排以下檢查：</p><ul><li style=\"margin-bottom: 10px;\"><strong>✳️心電圖：</strong>雖然基本上如果只用靜態心電圖檢測，通常看不出什麼問題，因為心悸並不一定會在檢測時發作。但是心電圖仍然可以幫助醫師了解，患者的心臟有沒有其他可能導致心悸的問題。</li><li style=\"margin-bottom: 10px;\"><strong>✳️霍特連續心電圖：</strong>記錄24小時內的心臟活動變化。這種方式能夠更容易掌握不知道什麼時候會出現的心悸狀況，並記錄下來。</li><li style=\"margin-bottom: 10px;\"><strong>✳️實驗室資料：</strong><br>✔️ <strong>全血細胞計數</strong> ➡️ 可評估有無貧血<br>✔️ <strong>甲狀腺功能檢查</strong> ➡️ 可檢測有無甲狀腺亢進</li></ul><hr style=\"border: 0; border-top: 1px dashed #ccc; margin: 25px 0;\"><p style=\"font-size: 0.85rem; color: #888;\"><strong>🔹資料來源：</strong>hello醫師</p>"
    }
    
]